oceanea/__init__.py
oceanea-0.0.1.dist-info/LICENSE
oceanea-0.0.1.dist-info/METADATA
oceanea-0.0.1.dist-info/WHEEL
oceanea-0.0.1.dist-info/entry_points.txt
oceanea-0.0.1.dist-info/top_level.txt
oceanea-0.0.1.dist-info/RECORD
