Metadata-Version: 2.1
Name: oceanea
Version: 0.0.1
Summary: Empirical functions for the exploratory analysis of physical oceanography data.
Home-page: https://github.com/williamedge/oceanea
Author: William Edge
Author-email: william.edge@uwa.edu.au
License: BSD-3-Clause
Project-URL: Bug Tracker, https://github.com/williamedge/oceanea/issues
Project-URL: Changelog, https://github.com/williamedge/oceanea/releases
Classifier: Programming Language :: Python :: 3
Classifier: License :: OSI Approved :: BSD License
Classifier: Intended Audience :: Developers
Requires-Python: >=3.7
License-File: LICENSE
Requires-Dist: numpy
Requires-Dist: scipy
Requires-Dist: xarray
Requires-Dist: matplotlib
